uw_kws/VERSION
uw_kws/__init__.py
uw_kws/dao.py
uw_kws/models.py
uw_kws/test.py
uw_kws/utilities.py
uw_kws/resources/kws/file/key/v1/encryption/ee99defd-baee-43b0-9e1e-f8238dd106bb.json
uw_kws/resources/kws/file/key/v1/type/uw-student-registration/encryption/current.json
uw_kws/tests/__init__.py
uw_kws/tests/test_key.py
UW_RestClients_KWS-1.1.2.dist-info/LICENSE
UW_RestClients_KWS-1.1.2.dist-info/METADATA
UW_RestClients_KWS-1.1.2.dist-info/WHEEL
UW_RestClients_KWS-1.1.2.dist-info/top_level.txt
UW_RestClients_KWS-1.1.2.dist-info/RECORD
