Metadata-Version: 2.1
Name: UW-RestClients-KWS
Version: 1.1.2
Summary: A library for connecting to the KWS at the University of Washington
Home-page: https://github.com/uw-it-aca/uw-restclients-kws
Author: UW-IT T&LS
Author-email: aca-it@uw.edu
License: Apache License, Version 2.0
Classifier: Intended Audience :: Developers
Classifier: License :: OSI Approved :: Apache Software License
Classifier: Operating System :: OS Independent
Classifier: Programming Language :: Python
License-File: LICENSE
Requires-Dist: UW-RestClients-Core <2.0,>1.4
Requires-Dist: python-dateutil
Requires-Dist: mock
